flowcut/__init__.py
flowcut/clip_encoder.py
flowcut/llava_arch.py
flowcut/llava_llama_flowcut.py
flowcut/main.py
flowcut/modeling_clip_flowcut.py
flowcut/modeling_llama_flowcut.py
flowcut/utils_flowcut.py
flowcut-1.0.2.dist-info/METADATA
flowcut-1.0.2.dist-info/WHEEL
flowcut-1.0.2.dist-info/top_level.txt
flowcut-1.0.2.dist-info/RECORD
