Metadata-Version: 2.1
Name: flowcut
Version: 1.0.2
Summary: FlowCut: Rethinking Redundancy via Information Flow for Efficient Vision-Language Models
Home-page: https://github.com/TungChintao/FlowCut
Author: Jintao Tong
Author-email: jintaotong@hust.edu.cn
Classifier: Programming Language :: Python :: 3
Classifier: License :: OSI Approved :: Apache Software License
Classifier: Operating System :: OS Independent
Requires-Python: >=3.6
